masterful_gui/__init__.py
masterful_gui/__main__.py
masterful_gui/application.py
masterful_gui/main.py
masterful_gui/manage.py
masterful_gui/manage_dev.py
masterful_gui/program.py
masterful_gui/server.py
masterful_gui/version.py
masterful_gui/backend/__init__.py
masterful_gui/backend/asgi.py
masterful_gui/backend/settings.py
masterful_gui/backend/settings_dev.py
masterful_gui/backend/urls.py
masterful_gui/backend/wsgi.py
masterful_gui/backend/apps/__init__.py
masterful_gui/backend/apps/api/__init__.py
masterful_gui/backend/apps/api/admin.py
masterful_gui/backend/apps/api/apps.py
masterful_gui/backend/apps/api/dataset_spec_scanner.py
masterful_gui/backend/apps/api/models.py
masterful_gui/backend/apps/api/policy_search_task_scanner.py
masterful_gui/backend/apps/api/scan_scheduler.py
masterful_gui/backend/apps/api/serializers.py
masterful_gui/backend/apps/api/tests.py
masterful_gui/backend/apps/api/views.py
masterful_gui/backend/apps/api/migrations/0001_initial.py
masterful_gui/backend/apps/api/migrations/0002_rename_customer_model_metrics_policysearchtask_presearch_model_val_metrics.py
masterful_gui/backend/apps/api/migrations/0003_datasetspec.py
masterful_gui/backend/apps/api/migrations/0004_auto_20210917_1440.py
masterful_gui/backend/apps/api/migrations/0005_policysearchtask_engine_version.py
masterful_gui/backend/apps/api/migrations/0006_auto_20220214_2209.py
masterful_gui/backend/apps/api/migrations/0007_policysearchtask_task_type.py
masterful_gui/backend/apps/api/migrations/__init__.py
masterful_gui/backend/proto/__init__.py
masterful_gui/backend/proto/action_pb2.py
masterful_gui/backend/proto/layer_pb2.py
masterful_gui/backend/proto/metadata_pb2.py
masterful_gui/backend/proto/metrics_pb2.py
masterful_gui/backend/proto/policy_pb2.py
masterful_gui/backend/proto/search_task_pb2.py
masterful_gui/data/sample_policy
masterful_gui/static/webpack-stats.dev.json
masterful_gui/static/admin/css/autocomplete.css
masterful_gui/static/admin/css/base.css
mful_gui_dev-0.4.0.dev20220314205013.dist-info/LICENSE
mful_gui_dev-0.4.0.dev20220314205013.dist-info/METADATA
mful_gui_dev-0.4.0.dev20220314205013.dist-info/WHEEL
mful_gui_dev-0.4.0.dev20220314205013.dist-info/entry_points.txt
mful_gui_dev-0.4.0.dev20220314205013.dist-info/top_level.txt
mful_gui_dev-0.4.0.dev20220314205013.dist-info/RECORD
